<?xml version="1.0" encoding="UTF-8"?>
<BMD source="BMD_Event_Cmmu_116_030_C.uasset" sourcePath="D:\Modding\Reloaded 2\Mods\p3r.asset.ukrainian\tools\dds_l10n\source\Xrd777\Events\Cinema\Event_Cmmu_116_030_C\BMD_Event_Cmmu_116_030_C.uasset" dialogs="20">
  <Speakers>
    <Speaker id="0" rawBytes="4E 6F 7A 6F 6D 69 20 53 75 65 6D 69 74 73 75">Нодзомі Суеміцу</Speaker>
    <Speaker id="1" rawBytes="52 61 6D 65 6E 20 53 68 6F 70 20 4F 77 6E 65 72">Власник раменної</Speaker>
  </Speakers>
  <Dialog id="0" name="MND_000_0_0" type="Message">
    <Page spk="FFFF"><![CDATA[{f 0 5 254}{f 2 1}У ресторані витає[n]знайомий запах риби.[n]{f 1 1}]]></Page>
  </Dialog>
  <Dialog id="1" name="MSG_001_0_0" type="Message">
    <Page spk="0000"><![CDATA[{f 0 5 254}{f 2 1}{f 4 5 116 1 -1 -1 0 0}{f 3 1 1 0 0 1 0 0}Досить закусок?[n]{f 1 1}]]></Page>
  </Dialog>
  <Dialog id="2" name="MSG_001_3_0" type="Message">
    <Page spk="0000"><![CDATA[{f 0 5 254}{f 2 1}{f 4 5 116 1 -1 -1 0 0}{f 3 1 1 0 0 2 0 0}Пробачте, мосьпане! Дві миски як завжди! І, як зазвичай, надвелику![n]{f 1 1}]]></Page>
  </Dialog>
  <Dialog id="3" name="MSG_002_0_0" type="Message">
    <Page spk="0001"><![CDATA[{f 0 5 254}{f 2 1}{f 3 1 1 0 0 3 0 0}{f 5 21 0 1001}Уже несу.[n]{f 1 1}]]></Page>
  </Dialog>
  <Dialog id="4" name="MND_003_0_0" type="Message">
    <Page spk="FFFF"><![CDATA[{f 0 5 254}{f 2 1}Наші миски[n]замінили на дві нові, свіжі.[n]{f 1 1}]]></Page>
  </Dialog>
  <Dialog id="5" name="MSG_004_0_0" type="Message">
    <Page spk="0000"><![CDATA[{f 0 5 254}{f 2 1}{f 4 5 116 1 -1 -1 0 0}{f 3 1 1 0 0 4 0 0}Як скуштуєш — дороги назад уже не буде, друже.[n]{f 1 1}]]></Page>
    <Page spk="0000"><![CDATA[{f 0 5 254}{f 2 1}{f 4 5 116 1 -1 -1 0 0}{f 3 1 1 0 0 5 0 0}Тан-Тан-Тан Рамен! Так! Цілих три — рахуйте самі — три Тани![n]{f 1 1}]]></Page>
  </Dialog>
  <Dialog id="6" name="MSG_004_3_0" type="Message">
    <Page spk="0000"><![CDATA[{f 0 5 254}{f 2 1}{f 4 5 116 1 -1 -1 0 0}{f 3 1 1 0 0 6 0 0}Це коштовна перлина секретного меню — навіть краще за миску Хаґакуре![n]{f 1 1}]]></Page>
    <Page spk="0000"><![CDATA[{f 0 5 254}{f 2 1}{f 4 5 116 1 -1 -1 0 0}{f 3 1 1 0 0 7 0 0}Простий, солоний бульйон у поєднанні з густим гострим місо-соусом... Це як мікрокосм дива створення![n]{f 1 1}]]></Page>
  </Dialog>
  <Dialog id="7" name="MND_005_0_0" type="Message">
    <Page spk="FFFF"><![CDATA[{f 0 5 254}{f 2 1}Ого![n]{f 1 1}]]></Page>
    <Page spk="FFFF"><![CDATA[{f 0 5 254}{f 2 1}Неймовірний смак[n]змиває всі мої турботи![n]{f 1 1}]]></Page>
  </Dialog>
  <Dialog id="8" name="MSG_006_0_0" type="Message">
    <Page spk="0000"><![CDATA[{f 0 5 254}{f 2 1}{f 4 5 116 0 -1 -1 0 0}{f 3 1 1 0 0 8 0 0}Усе завдяки секретному меню! Хоча... як люди його знайдуть, якщо воно секретне?[n]{f 1 1}]]></Page>
    <Page spk="0000"><![CDATA[{f 0 5 254}{f 2 1}{f 4 5 116 1 -1 -1 0 0}{f 3 1 1 0 0 9 0 0}{f 4 23 0 116 1 25 25}Та байдуже. Що більше думаю, то сильніше хочу їсти.[n]{f 1 1}]]></Page>
  </Dialog>
  <Dialog id="9" name="MSG_007_0_0" type="Message">
    <Page spk="0000"><![CDATA[{f 0 5 254}{f 2 1}{f 4 5 116 0 -1 -1 0 0}{f 3 1 1 0 0 10 0 0}О, пане! Будьте ласкаві, не виливайте цю першу миску! У мене з тим супом іще незакінчені справи![n]{f 1 1}]]></Page>
  </Dialog>
  <Dialog id="10" name="MSG_008_0_0" type="Message">
    <Page spk="0000"><![CDATA[{f 0 5 254}{f 2 1}{f 4 5 116 1 -1 -1 0 0}{f 3 1 1 0 0 11 0 0}Це велика честь для тебе. Ти — лише друга людина, яка це куштує після мене.[n]{f 1 1}]]></Page>
    <Page spk="0000"><![CDATA[{f 0 5 254}{f 2 1}{f 4 5 116 1 -1 -1 0 0}{f 3 1 1 0 0 12 0 0}Не забудь подмухати на локшину, щоб охолола.[n]{f 1 1}]]></Page>
  </Dialog>
  <Dialog id="11" name="MND_009_0_0" type="Message">
    <Page spk="FFFF"><![CDATA[{f 0 5 254}{f 2 1}Я справді відчуваю доброту Суеміцу.[n]{f 1 1}]]></Page>
    <Page spk="FFFF"><![CDATA[{f 0 5 254}{f 2 1}Я відчуваю, що наші стосунки зміцнились...[n]{f 1 1}]]></Page>
  </Dialog>
  <Dialog id="12" name="MSG_010_0_0" type="Message">
    <Page spk="0000"><![CDATA[{f 0 5 254}{f 2 1}{f 4 5 116 1 -1 -1 0 0}{f 3 1 1 0 0 13 0 0}Який же ти щасливець. У тебе ж є такий друг, як я![n]{f 1 1}]]></Page>
    <Page spk="0000"><![CDATA[{f 0 5 254}{f 2 1}{f 4 5 116 3 -1 -1 0 0}{f 3 1 1 0 0 14 0 0}{f 4 23 0 116 3 25 25}І до твого відома, такого не буде з моїм молодшим братом, бо брат Короля гурманів — це ще не сам Король гурманів![n]{f 1 1}]]></Page>
  </Dialog>
  <Dialog id="13" name="MSG_010_3_0" type="Message">
    <Page spk="0000"><![CDATA[{f 0 5 254}{f 2 1}{f 4 5 116 1 -1 -1 0 0}{f 3 1 1 0 0 15 0 0}Ну що, «пізнав» мене, га? Хто я такий? Хочу почути це з твоїх вуст![n]{f 1 1}]]></Page>
  </Dialog>
  <Dialog id="14" name="SEL_011_0_0" type="Selection">
    <Option><![CDATA[{f 0 5 254}{f 2 1}Нодзомі Суеміцу.]]></Option>
    <Option><![CDATA[{f 0 5 254}{f 2 1}Король гурманів.]]></Option>
  </Dialog>
  <Dialog id="15" name="MSG_012_0_0" type="Message">
    <Page spk="0000"><![CDATA[{f 0 5 254}{f 2 1}{f 4 5 116 3 -1 -1 0 0}{f 3 1 1 0 0 16 0 0}Ем, ну... Так, мабуть, ти правий... Зовні блиск, а мізків катма, правда?[n]{f 1 1}]]></Page>
  </Dialog>
  <Dialog id="16" name="MSG_013_0_0" type="Message">
    <Page spk="0000"><![CDATA[{f 0 5 254}{f 2 1}{f 4 5 116 1 -1 -1 0 0}{f 3 1 1 0 0 17 0 0}{f 5 13 19 15 116}Ой, не так голосно! Ти що, хочеш мене зганьбити? Тримай моє варене яйце. Я трохи над’їв, але їсти можна![n]{f 1 1}]]></Page>
  </Dialog>
  <Dialog id="17" name="MSG_014_0_0" type="Message">
    <Page spk="0000"><![CDATA[{f 0 5 254}{f 2 1}{f 4 5 116 4 -1 -1 0 0}{f 3 1 1 0 0 18 0 0}Йой! Досить балачок! Якщо не почнемо їсти, їжа стане жорсткою й без смаку![n]{f 1 1}]]></Page>
  </Dialog>
  <Dialog id="18" name="MSG_014_5_0" type="Message">
    <Page spk="0000"><![CDATA[{f 0 5 254}{f 2 1}{f 4 5 116 2 -1 -1 0 1}{f 3 1 1 0 0 19 0 0}Пане! Пане! Ви зберегли ту першу миску, так? Бо вона мені ще знадобиться![n]{f 1 1}]]></Page>
  </Dialog>
  <Dialog id="19" name="MND_015_0_0" type="Message">
    <Page spk="FFFF"><![CDATA[{f 0 5 254}{f 2 1}Ми з Суеміцу доїли наш рамен[n]і я повернувся до гуртожитку.[n]{f 1 1}]]></Page>
  </Dialog>
</BMD>
