<?xml version="1.0" encoding="UTF-8"?>
<BMD source="BMD_Event_Cmmu_117_060_C.uasset" sourcePath="D:\Modding\Reloaded 2\Mods\p3r.asset.ukrainian\tools\dds_l10n\source\Xrd777\Events\Cinema\Event_Cmmu_117_060_C\BMD_Event_Cmmu_117_060_C.uasset" dialogs="22">
  <Speakers>
    <Speaker id="0" rawBytes="41 6B 69 6E 61 72 69 20 4B 61 6D 69 6B 69">Акінарі Камікі</Speaker>
  </Speakers>
  <Dialog id="0" name="MSG_000_0_0" type="Message">
    <Page spk="0000"><![CDATA[{f 0 5 254}{f 2 1}{f 4 5 117 0 -1 -1 0 0}{f 3 1 1 0 0 1 0 0}Скажи, а як ти ставишся до рожевого алігатора?[n]{f 1 1}]]></Page>
  </Dialog>
  <Dialog id="1" name="SEL_001_0_0" type="Selection">
    <Option><![CDATA[{f 0 5 254}{f 2 1}Звучить норм для мене.]]></Option>
    <Option><![CDATA[{f 0 5 254}{f 2 1}Я не знаю...]]></Option>
    <Option><![CDATA[{f 0 5 254}{f 2 1}Е-е, що?]]></Option>
  </Dialog>
  <Dialog id="2" name="MSG_002_0_0" type="Message">
    <Page spk="0000"><![CDATA[{f 0 5 254}{f 2 1}{f 4 5 117 1 -1 -1 0 0}{f 3 1 1 0 0 2 0 0}{f 5 13 20 15 117}Я так і думав. Я знав, що ти зрозумієш.[n]{f 1 1}]]></Page>
  </Dialog>
  <Dialog id="3" name="MSG_003_0_0" type="Message">
    <Page spk="0000"><![CDATA[{f 0 5 254}{f 2 1}{f 4 5 117 0 -1 -1 0 0}{f 3 1 1 0 0 3 0 0}У житті буває багато ситуацій, коли люди не погоджуються між собою...[n]{f 1 1}]]></Page>
    <Page spk="0000"><![CDATA[{f 0 5 254}{f 2 1}{f 4 5 117 0 -1 -1 0 0}{f 3 1 1 0 0 4 0 0}Хоча... мабуть, є багато речей, з якими можна не погоджуватись.[n]{f 1 1}]]></Page>
  </Dialog>
  <Dialog id="4" name="MSG_004_0_0" type="Message">
    <Page spk="0000"><![CDATA[{f 0 5 254}{f 2 1}{f 4 5 117 0 -1 -1 0 0}{f 3 1 1 0 0 5 0 0}Ой, вибач... Я просто задумався про дещо.[n]{f 1 1}]]></Page>
  </Dialog>
  <Dialog id="5" name="MSG_005_0_0" type="Message">
    <Page spk="0000"><![CDATA[{f 0 5 254}{f 2 1}{f 4 5 117 0 -1 -1 0 0}{f 3 1 1 0 0 6 0 0}Розумієш, це головний герой історії, яку я пишу...[n]{f 1 1}]]></Page>
    <Page spk="0000"><![CDATA[{f 0 5 254}{f 2 1}{f 4 5 117 0 -1 -1 0 0}{f 3 1 1 0 0 7 0 0}Він народився в розкішному зеленому лісі, але виявився рожевим.[n]{f 1 1}]]></Page>
  </Dialog>
  <Dialog id="6" name="MSG_005_3_0" type="Message">
    <Page spk="0000"><![CDATA[{f 0 5 254}{f 2 1}{f 4 5 117 0 -1 -1 0 0}{f 3 1 1 0 0 8 0 0}Він так виділяється, що не може полювати, тож постійно голодний.[n]{f 1 1}]]></Page>
    <Page spk="0000"><![CDATA[{f 0 5 254}{f 2 1}{f 4 5 117 0 -1 -1 0 0}{f 3 1 1 0 0 9 0 0}Інші тварини його не люблять, називають огидним... ніби він проклятий.[n]{f 1 1}]]></Page>
  </Dialog>
  <Dialog id="7" name="MSG_005_7_0" type="Message">
    <Page spk="0000"><![CDATA[{f 0 5 254}{f 2 1}{f 4 5 117 0 -1 -1 0 0}{f 3 1 1 0 0 10 0 0}Отже, він звик жити на самоті... Але одного дня він знайшов друга.[n]{f 1 1}]]></Page>
    <Page spk="0000"><![CDATA[{f 0 5 254}{f 2 1}{f 4 5 117 0 -1 -1 0 0}{f 3 1 1 0 0 11 0 0}Це був маленький птах, якому було важко літати...[n]{f 1 1}]]></Page>
    <Page spk="0000"><![CDATA[{f 0 5 254}{f 2 1}{f 4 5 117 0 -1 -1 0 0}{f 3 1 1 0 0 12 0 0}Щодня пташка сідала на спину рожевого алігатора й тренувалась.[n]{f 1 1}]]></Page>
  </Dialog>
  <Dialog id="8" name="MSG_006_0_0" type="Message">
    <Page spk="0000"><![CDATA[{f 0 5 254}{f 2 1}{f 4 5 117 1 -1 -1 0 0}{f 3 1 1 0 0 13 0 0}Мені трохи соромно розповідати тобі про це...[n]{f 1 1}]]></Page>
    <Page spk="0000"><![CDATA[{f 0 5 254}{f 2 1}{f 4 5 117 0 -1 -1 0 0}{f 3 1 1 0 0 14 0 0}{f 4 23 0 117 0 25 25}То що ти думаєш?[n]{f 1 1}]]></Page>
  </Dialog>
  <Dialog id="9" name="SEL_007_0_0" type="Selection">
    <Option><![CDATA[{f 0 5 254}{f 2 1}Звучить цікаво.]]></Option>
    <Option><![CDATA[{f 0 5 254}{f 2 1}Потрібна допрацювати...]]></Option>
    <Option><![CDATA[{f 0 5 254}{f 2 1}Хотів би почути більше.]]></Option>
  </Dialog>
  <Dialog id="10" name="MSG_008_0_0" type="Message">
    <Page spk="0000"><![CDATA[{f 0 5 254}{f 2 1}{f 4 5 117 0 -1 -1 0 0}{f 3 1 1 0 0 15 0 0}{f 5 13 20 15 117}Справді?[n]{f 1 1}]]></Page>
    <Page spk="0000"><![CDATA[{f 0 5 254}{f 2 1}{f 4 5 117 0 -1 -1 0 0}{f 3 1 1 0 0 16 0 0}Я ніколи раніше не писав історій, тож хвилююсь, що в мене не вийде добре.[n]{f 1 1}]]></Page>
  </Dialog>
  <Dialog id="11" name="MSG_008_5_0" type="Message">
    <Page spk="0000"><![CDATA[{f 0 5 254}{f 2 1}{f 4 5 117 0 -1 -1 0 0}{f 3 1 1 0 0 17 0 0}Але головне — що я пишу її для себе.[n]{f 1 1}]]></Page>
    <Page spk="0000"><![CDATA[{f 0 5 254}{f 2 1}{f 4 5 117 0 -1 -1 0 0}{f 3 1 1 0 0 18 0 0}Можливо, колись я покажу тобі весь роман...[n]{f 1 1}]]></Page>
  </Dialog>
  <Dialog id="12" name="MSG_009_0_0" type="Message">
    <Page spk="0000"><![CDATA[{f 0 5 254}{f 2 1}{f 4 5 117 0 -1 -1 0 0}{f 3 1 1 0 0 19 0 0}Розумію...[n]{f 1 1}]]></Page>
    <Page spk="0000"><![CDATA[{f 0 5 254}{f 2 1}{f 4 5 117 0 -1 -1 0 0}{f 3 1 1 0 0 20 0 0}Ну... це мій перший досвід написання подібної історії, тож вона не буде ідеальною.[n]{f 1 1}]]></Page>
  </Dialog>
  <Dialog id="13" name="MSG_009_5_0" type="Message">
    <Page spk="0000"><![CDATA[{f 0 5 254}{f 2 1}{f 4 5 117 0 -1 -1 0 0}{f 3 1 1 0 0 21 0 0}Але я пишу її для себе. Саме це має значення.[n]{f 1 1}]]></Page>
    <Page spk="0000"><![CDATA[{f 0 5 254}{f 2 1}{f 4 5 117 0 -1 -1 0 0}{f 3 1 1 0 0 22 0 0}Сподіваюся, ти зможеш щось винести з цієї історії, коли вона буде завершена...[n]{f 1 1}]]></Page>
  </Dialog>
  <Dialog id="14" name="MSG_010_0_0" type="Message">
    <Page spk="0000"><![CDATA[{f 0 5 254}{f 2 1}{f 4 5 117 0 -1 -1 0 0}{f 3 1 1 0 0 23 0 0}{f 5 13 20 5 117}Ну, поки що це ще в процесі роботи...[n]{f 1 1}]]></Page>
    <Page spk="0000"><![CDATA[{f 0 5 254}{f 2 1}{f 4 5 117 0 -1 -1 0 0}{f 3 1 1 0 0 24 0 0}Я ніколи не пробував писати історію... тож, можливо, я в цьому не дуже вправний.[n]{f 1 1}]]></Page>
  </Dialog>
  <Dialog id="15" name="MSG_010_5_0" type="Message">
    <Page spk="0000"><![CDATA[{f 0 5 254}{f 2 1}{f 4 5 117 0 -1 -1 0 0}{f 3 1 1 0 0 25 0 0}Але я пишу її для себе. Саме це має значення.[n]{f 1 1}]]></Page>
    <Page spk="0000"><![CDATA[{f 0 5 254}{f 2 1}{f 4 5 117 0 -1 -1 0 0}{f 3 1 1 0 0 26 0 0}Я сподіваюся, що ти зможеш винести з неї щось позитивне...[n]{f 1 1}]]></Page>
  </Dialog>
  <Dialog id="16" name="MSG_011_0_0" type="Message">
    <Page spk="0000"><![CDATA[{f 0 5 254}{f 2 1}{f 4 5 117 0 -1 -1 0 0}{f 3 1 1 0 0 27 0 0}Насправді я вигадав її нещодавно.[n]{f 1 1}]]></Page>
    <Page spk="0000"><![CDATA[{f 0 5 254}{f 2 1}{f 4 5 117 0 -1 -1 0 0}{f 3 1 1 0 0 28 0 0}Я вирішив написати зворушливу історію для самого себе.[n]{f 1 1}]]></Page>
    <Page spk="0000"><![CDATA[{f 0 5 254}{f 2 1}{f 4 5 117 0 -1 -1 0 0}{f 3 1 1 0 0 29 0 0}Я хочу, щоб вона була сповнена надії... про те, як знайти сенс у житті.[n]{f 1 1}]]></Page>
  </Dialog>
  <Dialog id="17" name="MSG_011_5_0" type="Message">
    <Page spk="0000"><![CDATA[{f 0 5 254}{f 2 1}{f 4 5 117 1 -1 -1 0 0}{f 3 1 1 0 0 30 0 0}Я думаю про тебе, коли пишу... Ніби чую, як ти кажеш мені: «Не помирай поки що».[n]{f 1 1}]]></Page>
  </Dialog>
  <Dialog id="18" name="MND_012_0_0" type="Message">
    <Page spk="FFFF"><![CDATA[{f 0 5 254}{f 2 1}Камікі слабко усміхнувся...[n]{f 1 1}]]></Page>
    <Page spk="FFFF"><![CDATA[{f 0 5 254}{f 2 1}Я відчуваю, що наші стосунки зміцнились...[n]{f 1 1}]]></Page>
  </Dialog>
  <Dialog id="19" name="MSG_013_0_0" type="Message">
    <Page spk="0000"><![CDATA[{f 0 5 254}{f 2 1}{f 4 5 117 0 -1 -1 0 0}{f 3 1 1 0 0 31 0 0}Скоро підніметься вітер... Тепер я можу відчувати такі речі.[n]{f 1 1}]]></Page>
    <Page spk="0000"><![CDATA[{f 0 5 254}{f 2 1}{f 4 5 117 0 -1 -1 0 0}{f 3 1 1 0 0 32 0 0}Сподіваюся, в мене ще є час...[n]{f 1 1}]]></Page>
  </Dialog>
  <Dialog id="20" name="MSG_014_0_0" type="Message">
    <Page spk="0000"><![CDATA[{f 0 5 254}{f 2 1}{f 4 5 117 0 -1 -1 0 0}{f 3 1 1 0 0 33 0 0}Нам час іти. Я б хотів ще побачити тебе якось.[n]{f 1 1}]]></Page>
  </Dialog>
  <Dialog id="21" name="MND_015_0_0" type="Message">
    <Page spk="FFFF"><![CDATA[{f 0 5 254}{f 2 1}Я попрощався з Камікі[n]та вирушив назад до гуртожитку.[n]{f 1 1}]]></Page>
  </Dialog>
</BMD>
