<?xml version="1.0" encoding="UTF-8"?>
<BMD source="BMD_Event_Main_210_230_C.uasset" sourcePath="D:\Modding\Reloaded 2\Mods\p3r.asset.ukrainian\tools\dds_l10n\source\Xrd777\Events\Cinema\Event_Main_210_230_C\BMD_Event_Main_210_230_C.uasset" dialogs="8">
  <Speakers>
    <Speaker id="0" rawBytes="4E 61 74 73 75 6B 69 20 4D 6F 72 69 79 61 6D 61">Нацукі Моріяма</Speaker>
    <Speaker id="1" rawBytes="4B 65 6E 6A 69 20 54 6F 6D 6F 63 68 69 6B 61">Кенджі ТомочікаКенджі Томочіка</Speaker>
    <Speaker id="2" rawBytes="59 75 6B 6F 20 4E 69 73 68 69 77 61 6B 69">Юко Нішівакі</Speaker>
    <Speaker id="3" rawBytes="4B 61 7A 75 73 68 69 20 4D 69 79 61 6D 6F 74 6F">Кадзуші Міямото</Speaker>
    <Speaker id="4" rawBytes="43 68 69 68 69 72 6F 20 46 75 73 68 69 6D 69">Чіхіро Фушімі</Speaker>
  </Speakers>
  <Dialog id="0" name="MSG_000_0_0" type="Message">
    <Page spk="0000"><![CDATA[{f 0 5 254}{f 2 1}{f 4 5 223 2 6 -1 0 0}{f 3 1 1 0 0 1 0 0}Okay, gotta stay calm...[n]{f 1 1}]]></Page>
    <Page spk="0000"><![CDATA[{f 0 5 254}{f 2 1}{f 4 5 223 2 6 -1 0 0}{f 3 1 1 0 0 2 0 0}That's right, like Fuuka was when she saved me...[n]{f 1 1}]]></Page>
  </Dialog>
  <Dialog id="1" name="MSG_001_0_0" type="Message">
    <Page spk="0000"><![CDATA[{f 0 5 254}{f 2 1}{f 4 5 223 0 6 -1 0 0}{f 3 1 1 0 0 3 0 0}I'm the one who said we're always connected...[n]{f 1 1}]]></Page>
    <Page spk="0000"><![CDATA[{f 0 5 254}{f 2 1}{f 4 5 223 0 6 -1 0 0}{f 3 1 1 0 0 4 0 0}That's how I know you're still hanging in there, Fuuka.[n]{f 1 1}]]></Page>
  </Dialog>
  <Dialog id="2" name="MSG_002_0_0" type="Message">
    <Page spk="0000"><![CDATA[{f 0 5 254}{f 2 1}{f 4 5 223 3 6 -1 0 0}{f 3 1 1 0 0 5 0 0}I'm scared as hell right now...[n]{f 1 1}]]></Page>
    <Page spk="0000"><![CDATA[{f 0 5 254}{f 2 1}{f 4 5 223 3 6 -1 0 0}{f 3 1 1 0 0 6 0 0}But... I know I can't give up![n]{f 1 1}]]></Page>
  </Dialog>
  <Dialog id="3" name="MSG_003_0_0" type="Message">
    <Page spk="0000"><![CDATA[{f 0 5 254}{f 2 1}{f 4 5 223 0 6 -1 0 0}{f 3 1 1 0 0 7 0 0}Right, Fuuka!?[n]{f 1 1}]]></Page>
  </Dialog>
  <Dialog id="4" name="MSG_004_0_0" type="Message">
    <Page spk="0001"><![CDATA[{f 0 5 254}{f 2 1}{f 4 5 101 4 6 -1 0 0}{f 3 1 1 0 0 8 0 0}Wh-What's going on!?[n]{f 1 1}]]></Page>
  </Dialog>
  <Dialog id="5" name="MSG_005_0_0" type="Message">
    <Page spk="0002"><![CDATA[{f 0 5 254}{f 2 1}{f 4 5 106 4 6 -1 0 0}{f 3 1 1 0 0 9 0 0}A-Am I dreaming!?[n]{f 1 1}]]></Page>
  </Dialog>
  <Dialog id="6" name="MSG_006_0_0" type="Message">
    <Page spk="0003"><![CDATA[{f 0 5 254}{f 2 1}{f 4 5 105 4 101 -1 0 0}{f 3 1 1 0 0 10 0 0}Oh man, what am I gonna do...?[n]{f 1 1}]]></Page>
  </Dialog>
  <Dialog id="7" name="MSG_007_0_0" type="Message">
    <Page spk="0004"><![CDATA[{f 0 5 254}{f 2 1}{f 4 5 109 3 6 -1 0 0}{f 3 1 1 0 0 11 0 0}How can this be happening...?[n]{f 1 1}]]></Page>
  </Dialog>
</BMD>
